audalign/__init__.py
audalign/datalign.py
audalign/filehandler.py
audalign/align/__init__.py
audalign/config/__init__.py
audalign/config/correlation.py
audalign/config/correlation_spectrogram.py
audalign/config/fingerprint.py
audalign/config/visual.py
audalign/recognizers/__init__.py
audalign/recognizers/correcognize/__init__.py
audalign/recognizers/correcognize/correcognize.py
audalign/recognizers/correcognizeSpectrogram/__init__.py
audalign/recognizers/correcognizeSpectrogram/correcognize_spectrogram.py
audalign/recognizers/fingerprint/__init__.py
audalign/recognizers/fingerprint/fingerprinter.py
audalign/recognizers/fingerprint/recognize.py
audalign/recognizers/visrecognize/__init__.py
audalign/recognizers/visrecognize/visrecognize.py
audalign-1.3.1.dist-info/METADATA
audalign-1.3.1.dist-info/WHEEL
audalign-1.3.1.dist-info/licenses/LICENSE.md
audalign-1.3.1.dist-info/RECORD
