Metadata-Version: 2.4
Name: audalign
Version: 1.3.1
Summary: Audio Alignment and Recognition in Python
Project-URL: Homepage, http://github.com/benfmiller/audalign
Project-URL: Documentation, https://github.com/benfmiller/audalign/wiki
Project-URL: Changelog, https://github.com/benfmiller/audalign/blob/main/CHANGELOG.md
Author-email: Ben Miller <benfmiller132@gmail.com>
Maintainer-email: Ben Miller <benfmiller132@gmail.com>
License-Expression: MIT
License-File: LICENSE.md
Keywords: align,alignment,audio,fingerprinting,music,python
Requires-Python: >=3.8
Requires-Dist: matplotlib==3.8.2
Requires-Dist: numpy==1.26.4
Requires-Dist: pydub==0.25.1
Requires-Dist: scipy==1.12.0
Requires-Dist: setuptools==59.6.0
Requires-Dist: tqdm==4.66.2
Provides-Extra: noisereduce
Requires-Dist: noisereduce==2.0.1; extra == 'noisereduce'
Requires-Dist: torch==2.2.0; extra == 'noisereduce'
Provides-Extra: test
Requires-Dist: pytest-xdist==3.1.0; extra == 'test'
Requires-Dist: pytest==8.0.0; extra == 'test'
Provides-Extra: visrecognize
Requires-Dist: pillow==10.2.0; extra == 'visrecognize'
Requires-Dist: scikit-image==0.19.3; extra == 'visrecognize'
